LICENSE
MANIFEST.in
README.md
env.yml
setup.cfg
setup.py
gnnom/__init__.py
gnnom/apply_nn.py
gnnom/gnnom_batch.py
gnnom/makemodel_scalar.py
gnnom.egg-info/PKG-INFO
gnnom.egg-info/SOURCES.txt
gnnom.egg-info/dependency_links.txt
gnnom.egg-info/top_level.txt
gnnom/models/smin.txt
gnnom/models/smax-index-129/dmax-3l-80u-idp/gnnom-dmax-5-129-e100-u80.json
gnnom/models/smax-index-129/dmax-3l-80u-idp/loss-gnnom-dmax-5-129-e100-u80.int
gnnom/models/smax-index-129/dmax-3l-80u-idp/weights-gnnom-dmax-5-129-e100-u80-0.int
gnnom/models/smax-index-129/dmax-3l-80u-idp/weights-gnnom-dmax-5-129-e100-u80-1.png
gnnom/models/smax-index-129/dmax-3l-80u-na/gnnom-dmax-5-129-e100-u80.h5
gnnom/models/smax-index-129/dmax-3l-80u-na/gnnom-dmax-5-129-e100-u80.json
gnnom/models/smax-index-129/dmax-3l-80u-na/loss-gnnom-dmax-5-129-e100-u80.int
gnnom/models/smax-index-129/dmax-3l-80u-na/weights-gnnom-dmax-5-129-e100-u80-0.int
gnnom/models/smax-index-129/dmax-3l-80u-na/weights-gnnom-dmax-5-129-e100-u80-1.png
gnnom/models/smax-index-129/dmax-3l-80u-p/gnnom-dmax-5-129-e100-u80.h5
gnnom/models/smax-index-129/dmax-3l-80u-p/gnnom-dmax-5-129-e100-u80.json
gnnom/models/smax-index-129/dmax-3l-80u-p/loss-gnnom-dmax-5-129-e100-u80.int
gnnom/models/smax-index-129/dmax-3l-80u-p/weights-gnnom-dmax-5-129-e100-u80-0.int
gnnom/models/smax-index-129/dmax-3l-80u-p/weights-gnnom-dmax-5-129-e100-u80-1.png
gnnom/models/smax-index-129/mw-3l-80u-idp/gnnom-mw-5-129-e100-u80.h5
gnnom/models/smax-index-129/mw-3l-80u-idp/gnnom-mw-5-129-e100-u80.json
gnnom/models/smax-index-129/mw-3l-80u-idp/loss-gnnom-mw-5-129-e100-u80.int
gnnom/models/smax-index-129/mw-3l-80u-idp/weights-gnnom-mw-5-129-e100-u80-0.int
gnnom/models/smax-index-129/mw-3l-80u-idp/weights-gnnom-mw-5-129-e100-u80-1.png
gnnom/models/smax-index-129/mw-3l-80u-na/gnnom-mw-5-129-e100-u80.h5
gnnom/models/smax-index-129/mw-3l-80u-na/gnnom-mw-5-129-e100-u80.json
gnnom/models/smax-index-129/mw-3l-80u-na/loss-gnnom-mw-5-129-e100-u80.int
gnnom/models/smax-index-129/mw-3l-80u-na/weights-gnnom-mw-5-129-e100-u80-0.int
